leboncoin/__init__.py
leboncoin/leboncoin.py
leboncoin-0.3.5.dist-info/LICENSE
leboncoin-0.3.5.dist-info/METADATA
leboncoin-0.3.5.dist-info/WHEEL
leboncoin-0.3.5.dist-info/top_level.txt
leboncoin-0.3.5.dist-info/RECORD
