Metadata-Version: 2.1
Name: leboncoin
Version: 0.3.5
Summary: This is a description
Home-page: https://github.com/Shinyhero36/Leboncoin-API-Wrapper
Author: Shinyhero36
License: GNU General Public License v3.0
Project-URL: Source, https://github.com/Shinyhero36/Leboncoin-API-Wrapper/
Project-URL: Tracker, https://github.com/Shinyhero36/Leboncoin-API-Wrapper/issues
Platform: UNKNOWN
Requires-Python: >=3.6
Requires-Dist: requests (>=2.25.0)
Requires-Dist: cloudscraper (>=1.2.48)
